[
  {
    "station_id": "S1",
    "code": "KAFD",
    "name": "KAFD - King Abdullah Financial District",
    "type": "interchange",
    "capacity_station": 4800,
    "capacity_platform": 3800,
    "train_capacity": { "train_total": 556, "carriage_capacity": 139, "cars_per_train": 4 },
    "line_color": "Blue",
    "served_lines": ["Blue", "Yellow", "Purple"]
  },
  {
    "station_id": "S2",
    "code": "STC",
    "name": "STC (Olaya)",
    "type": "urban",
    "capacity_station": 3200,
    "capacity_platform": 2600,
    "train_capacity": { "train_total": 556, "carriage_capacity": 139, "cars_per_train": 4 },
    "line_color": "Red",
    "served_lines": ["Red", "Blue"]
  },
  {
    "station_id": "S3",
    "code": "QASR",
    "name": "Qasr Al-Hokm",
    "type": "urban",
    "capacity_station": 4200,
    "capacity_platform": 3400,
    "train_capacity": { "train_total": 556, "carriage_capacity": 139, "cars_per_train": 4 },
    "line_color": "Orange",
    "served_lines": ["Orange", "Blue"]
  },
  {
    "station_id": "S4",
    "code": "MUSEUM",
    "name": "National Museum",
    "type": "cultural",
    "capacity_station": 2800,
    "capacity_platform": 2300,
    "train_capacity": { "train_total": 556, "carriage_capacity": 139, "cars_per_train": 4 },
    "line_color": "Green",
    "served_lines": ["Green", "Blue"]
  },
  {
    "station_id": "S5",
    "code": "AIRP_T12",
    "name": "Airport T1-2",
    "type": "airport",
    "capacity_station": 3800,
    "capacity_platform": 3000,
    "train_capacity": { "train_total": 556, "carriage_capacity": 139, "cars_per_train": 4 },
    "line_color": "Yellow",
    "served_lines": ["Yellow"]
  },
  {
    "station_id": "S6",
    "code": "First Industrial City",
    "name": "Western Station",
    "type": "intercity",
    "capacity_station": 1600,
    "capacity_platform": 1300,
    "train_capacity": { "train_total": 556, "carriage_capacity": 139, "cars_per_train": 4 },
    "line_color": "Orange",
    "served_lines": ["Orange"]
  }
]
